README.rst
resolver_deco.py
setup.py
resolver_deco.egg-info/PKG-INFO
resolver_deco.egg-info/SOURCES.txt
resolver_deco.egg-info/dependency_links.txt
resolver_deco.egg-info/requires.txt
resolver_deco.egg-info/top_level.txt