Metadata-Version: 1.1
Name: resolver-deco
Version: 1.0.2
Summary: Decorator for resolve function arguments
Home-page: https://github.com/zzzsochi/resolver_deco
Author: Alexander Zelenyak
Author-email: zzz.sochi@gmail.com
License: UNKNOWN
Keywords: dotted
Platform: UNKNOWN
Classifier: License :: OSI Approved :: BSD License
Classifier: Programming Language :: Python :: 3
Classifier: Development Status :: 5 - Production/Stable
